telegram/TelegramBot.py
telegram/__init__.py
telegram_alpa-0.0.1.dist-info/LICENSE
telegram_alpa-0.0.1.dist-info/METADATA
telegram_alpa-0.0.1.dist-info/WHEEL
telegram_alpa-0.0.1.dist-info/top_level.txt
telegram_alpa-0.0.1.dist-info/RECORD
